[
    {
        "numero": 242,
        "titulo": "Profundo é o saner de Deus, Criador",
        "compasso": "3/4",
        "interpretacao": null,
        "andamento": {
            "minimo": 63,
            "maximo": 76
        },
        "partitura": {
          "tipo": "png",
          "arquivo": "242.png"
        }
    },
    {
        "numero": 188,
        "titulo": "O Mestre habita em mim",
        "compasso": "4/4",
        "interpretacao": null,
        "andamento": {
            "minimo": 69,
            "maximo": 84
        },
        "partitura": {
          "tipo": "png",
          "arquivo": "188.png"
        }
    },
    {
        "numero": 200,
        "titulo": "Não te turbe o vosso coração",
        "compasso": "4/4",
        "interpretacao": null,
        "andamento": {
            "minimo": 60,
            "maximo": 80
        },
        "partitura": {
          "tipo": "png",
          "arquivo": "200.png"
        }
    },
    {
        "numero": 285,
        "titulo": "Glória e louvor a Jesus darei",
        "compasso": "4/4",
        "interpretacao": null,
        "andamento": {
            "minimo": 66,
            "maximo": 84
        },
        "partitura": {
          "tipo": "png",
          "arquivo": "285.png"
        }
    },
    {
        "numero": "Coro 1",
        "titulo": "Aleluia! Aleluia!",
        "compasso": "4/4",
        "interpretacao": null,
        "andamento": {
            "minimo": 60,
            "maximo": 80
        },
        "partitura": {
          "tipo": "png",
          "arquivo": "coro1.png"
        }
    },
    {
        "numero": 22,
        "titulo": "Guia-me, ó Senhor",
        "compasso": "6/8",
        "interpretacao": null,
        "andamento": {
            "minimo": 104,
            "maximo": 132
        },
        "partitura": {
          "tipo": "png",
          "arquivo": "022.png"
        }
    },
    {
        "numero": 138,
        "titulo": "Louvemos ao bom Jesus",
        "compasso": "6/8",
        "interpretacao": null,
        "andamento": {
            "minimo": 104,
            "maximo": 144
        },
        "partitura": {
          "tipo": "png",
          "arquivo": "138.png"
        }
    },
    {
        "numero": 41,
        "titulo": "O teu coração vem a Cristo entregar",
        "compasso": "9/8",
        "interpretacao": null,
        "andamento": {
            "minimo": 120,
            "maximo": 144
        },
        "partitura": {
          "tipo": "png",
          "arquivo": "041.png"
        }
    }
]